twetch2py
