Metadata-Version: 2.1
Name: twetch2py
Version: 0.0.4
Summary: A class-based implementation of the Twetch SDK for Python
Home-page: https://gitlab.com/cyphergato/twetch2py
Author: Cyphergato, LLC
Author-email: cyphergato@protonmail.com
License: MIT
Download-URL: https://gitlab.com/cyphergato/twetch2py/-/archive/master/twetch2py-master.tar.gz
Keywords: bitcoin,twetch,sdk,bsv
Platform: UNKNOWN
Classifier: Development Status :: 3 - Alpha
Classifier: Intended Audience :: Developers
Classifier: Topic :: Software Development :: Build Tools
Classifier: License :: OSI Approved :: MIT License
Classifier: Programming Language :: Python :: 3
Classifier: Programming Language :: Python :: 3.5
Classifier: Programming Language :: Python :: 3.6
Classifier: Programming Language :: Python :: 3.7
Classifier: Programming Language :: Python :: 3.8
